quantum_foam/__init__.py
quantum_foam/__main__.py
quantum_foam/api.py
quantum_foam/cli/commands/calver_command.py
quantum_foam/cli/commands/check_command.py
quantum_foam/cli/commands/pvi_command.py
quantum_foam/cli/commands/pypi_command.py
quantum_foam/cli/commands/root_command.py
quantum_foam/cli/commands/semver_command.py
quantum_foam/cli/commands/solover_command.py
quantum_foam/cli/styling/__init__.py
quantum_foam/cli/styling/themes.py
quantum_foam/constants.py
quantum_foam-0.4.0.dist-info/METADATA
quantum_foam-0.4.0.dist-info/WHEEL
quantum_foam-0.4.0.dist-info/entry_points.txt
quantum_foam-0.4.0.dist-info/licenses/LICENCE
quantum_foam-0.4.0.dist-info/RECORD
