Metadata-Version: 2.4
Name: quantum-foam
Version: 0.4.0
Summary: Simple and minimal version tag converter.
License: MIT
License-File: LICENCE
Author: Manoel Pereira de Queiroz
Author-email: mpq.dev@pm.me
Maintainer: Manoel Pereira de Queiroz
Maintainer-email: mpq.dev@pm.me
Requires-Python: >=3.11
Classifier: Development Status :: 1 - Planning
Classifier: Environment :: Console
Classifier: License :: OSI Approved :: MIT License
Classifier: Operating System :: OS Independent
Classifier: Programming Language :: Python :: 3
Classifier: Programming Language :: Python :: 3.11
Classifier: Programming Language :: Python :: 3.12
Classifier: Programming Language :: Python :: 3.13
Classifier: Programming Language :: Python :: 3.14
Classifier: Topic :: Software Development :: Libraries :: Python Modules
Classifier: Topic :: Terminals
Requires-Dist: click (>=8.1.0,<8.2.0)
Requires-Dist: packaging (>=25.0,<26.0)
Requires-Dist: rich (>=14.2.0,<15.0.0)
Requires-Dist: semver (>=3.0.4,<4.0.0)
Requires-Dist: typer[all] (>=0.20.0,<0.21.0)
Project-URL: Contributing Guidelines, https://gitlab.com/galactipy/utilities/quantum-foam/-/tree/master/CONTRIBUTING.md
Project-URL: Homepage, https://gitlab.com/galactipy/utilities/quantum-foam
Project-URL: Repository, https://gitlab.com/galactipy/utilities/quantum-foam
Project-URL: Work Item Tracker, https://gitlab.com/galactipy/utilities/quantum-foam/-/issues
